loopbot/__init__.py
loopbot/_cli.py
loopbot/agent.py
loopbot/client.py
loopbot/errors.py
loopbot/events.py
loopbot/permissions.py
loopbot/response.py
loopbot/structured.py
loopbot/usage.py
loopbot-0.0.0.dev0.dist-info/METADATA
loopbot-0.0.0.dev0.dist-info/WHEEL
loopbot-0.0.0.dev0.dist-info/licenses/LICENSE
loopbot-0.0.0.dev0.dist-info/RECORD
