Metadata-Version: 2.4
Name: loopbot
Version: 0.0.0.dev0
Summary: Python SDK wrapper for the OpenCode AI coding agent.
Project-URL: Homepage, https://github.com/botassembly/loopbot
Project-URL: Documentation, https://loopbot.dev/
Project-URL: Repository, https://github.com/botassembly/loopbot
Project-URL: Issues, https://github.com/botassembly/loopbot/issues
Project-URL: Changelog, https://loopbot.dev/changelog/
Author-email: Ian Maurer <imaurer@gmail.com>
License-Expression: MIT
License-File: LICENSE
Keywords: agent,ai,anthropic,automation,claude,codex,devtool,gemini,llm,openai,sdk
Classifier: Development Status :: 4 - Beta
Classifier: Intended Audience :: Developers
Classifier: License :: OSI Approved :: MIT License
Classifier: Operating System :: OS Independent
Classifier: Programming Language :: Python :: 3
Classifier: Programming Language :: Python :: 3.10
Classifier: Programming Language :: Python :: 3.11
Classifier: Programming Language :: Python :: 3.12
Classifier: Programming Language :: Python :: 3.13
Classifier: Programming Language :: Python :: 3.14
Classifier: Topic :: Scientific/Engineering :: Artificial Intelligence
Classifier: Topic :: Software Development :: Code Generators
Classifier: Topic :: Software Development :: Libraries :: Python Modules
Classifier: Typing :: Typed
Requires-Python: >=3.10
Requires-Dist: pydantic>=2.0.0
Provides-Extra: dev
Requires-Dist: black>=23.7.0; extra == 'dev'
Requires-Dist: mkdocs-material>=9.5.0; extra == 'dev'
Requires-Dist: mkdocs>=1.6.0; extra == 'dev'
Requires-Dist: mkdocstrings[python]>=0.26.1; extra == 'dev'
Requires-Dist: mypy>=1.5.0; extra == 'dev'
Requires-Dist: pytest-asyncio>=0.21.0; extra == 'dev'
Requires-Dist: pytest-cov>=4.1.0; extra == 'dev'
Requires-Dist: pytest-html>=4.1.1; extra == 'dev'
Requires-Dist: pytest-mock>=3.11.0; extra == 'dev'
Requires-Dist: pytest>=7.4.0; extra == 'dev'
Requires-Dist: ruff>=0.0.285; extra == 'dev'
